{
    "title": "Como hacer un vaso multifuncional (caf\u00e9, agua, refesco, jugo, etc......)",
    "description": "Espero te halla gustado este video y si fue as\u00ed reg\u00e1lame un like.",
    "referenceId": "zyjiMrUTvKo",
    "date_created": "1474038879",
    "date_modified": "1486664392",
    "tags": "",
    "sourceId": "4",
    "VIDEO_LENGTH": "SHORT",
    "duration": "184",
    "status": "approved",
    "visibility": "1",
    "video_type": null,
    "id": "85322452",
    "loginId": "1758904",
    "entityType": "1",
    "sortOrder": "7",
    "entityIdParent": "85322389",
    "titleTextEncoded": "Como-hacer-un-vaso-multifuncional-caf\u00e9-agua-refesco-jugo-etc",
    "category": "",
    "settings": "",
    "asset": {
        "type": "youtube",
        "thumbnailUrl": "https:\/\/i.ytimg.com\/vi\/zyjiMrUTvKo\/hqdefault.jpg",
        "uploadDate": 1474038879,
        "videoId": "zyjiMrUTvKo",
        "title": "Como hacer un vaso multifuncional (caf\u00e9, agua, refesco, jugo, etc......)",
        "description": "Espero te halla gustado este video y si fue as\u00ed reg\u00e1lame un like.",
        "author": "ALUX GAMER TV PRO",
        "mediaDuration": 184,
        "prettyDuration": "00:03:04",
        "views": "22"
    },
    "transcripts": ""
}